libname/__init__.py
Topsis_new_package-0.0.1.dist-info/METADATA
Topsis_new_package-0.0.1.dist-info/WHEEL
Topsis_new_package-0.0.1.dist-info/top_level.txt
Topsis_new_package-0.0.1.dist-info/RECORD
